{
  "ticker": "ZTS",
  "timeframe": "5mins",
  "n_splits": 5,
  "test_size": 500,
  "scheme": "expanding",
  "embargo": 16,
  "purge": 16,
  "threshold_grid": [
    0.8,
    0.9
  ],
  "folds": [
    {
      "fold": 0,
      "n_train": 1577,
      "n_test": 500,
      "roc_auc": 0.6777396548138906,
      "pr_auc": 0.17658396112678798,
      "thresholds": [
        {
          "thr": 0.8,
          "n_trades": 0,
          "ev": -2.0
        },
        {
          "thr": 0.9,
          "n_trades": 0,
          "ev": -2.0
        }
      ]
    },
    {
      "fold": 1,
      "n_train": 2077,
      "n_test": 500,
      "roc_auc": 0.7082307902652448,
      "pr_auc": 0.23619283713873276,
      "thresholds": [
        {
          "thr": 0.8,
          "n_trades": 46,
          "ev": -0.9130434782608696
        },
        {
          "thr": 0.9,
          "n_trades": 15,
          "ev": 2.220446049250313e-16
        }
      ]
    },
    {
      "fold": 2,
      "n_train": 2577,
      "n_test": 500,
      "roc_auc": 0.7697228144989339,
      "pr_auc": 0.34686633579067755,
      "thresholds": [
        {
          "thr": 0.8,
          "n_trades": 1,
          "ev": -2.0
        },
        {
          "thr": 0.9,
          "n_trades": 0,
          "ev": -2.0
        }
      ]
    },
    {
      "fold": 3,
      "n_train": 3077,
      "n_test": 500,
      "roc_auc": 0.9096331643304503,
      "pr_auc": 0.5132684342255084,
      "thresholds": [
        {
          "thr": 0.8,
          "n_trades": 2,
          "ev": 0.5
        },
        {
          "thr": 0.9,
          "n_trades": 0,
          "ev": -2.0
        }
      ]
    },
    {
      "fold": 4,
      "n_train": 3577,
      "n_test": 500,
      "roc_auc": 0.6484741040901608,
      "pr_auc": 0.1668311564157537,
      "thresholds": [
        {
          "thr": 0.8,
          "n_trades": 4,
          "ev": -0.75
        },
        {
          "thr": 0.9,
          "n_trades": 1,
          "ev": -2.0
        }
      ]
    }
  ],
  "oof": {
    "n_samples": 2500,
    "oof_eval": {
      "oof_thresholds": [
        {
          "thr": 0.8,
          "n_trades": 53,
          "hits": 12,
          "hit_rate": 0.22641509433962265,
          "hit_rate_lb": 0.13454499977265524,
          "ev": -0.8679245283018868,
          "ev_lb": -1.3272750011367238
        },
        {
          "thr": 0.9,
          "n_trades": 16,
          "hits": 6,
          "hit_rate": 0.375,
          "hit_rate_lb": 0.18480982554752803,
          "ev": -0.125,
          "ev_lb": -1.0759508722623599
        }
      ],
      "best_oof_by_ev_lb": {
        "thr": 0.9,
        "n_trades": 16,
        "hits": 6,
        "hit_rate": 0.375,
        "hit_rate_lb": 0.18480982554752803,
        "ev": -0.125,
        "ev_lb": -1.0759508722623599
      }
    }
  },
  "metrics_mean": {
    "roc_auc": 0.742760105599736,
    "pr_auc": 0.28794854493949207
  },
  "metrics_std": {
    "roc_auc": 0.10354152321635772,
    "pr_auc": 0.144905576330926
  },
  "ev_at_recommended": {
    "per_fold": [
      2.220446049250313e-16,
      -2.0
    ],
    "mean": -0.9999999999999999,
    "std": 1.4142135623730951,
    "folds_covered": 2
  },
  "recommended_threshold": null,
  "recommended_by": null
}