{
  "ticker": "AWK",
  "timeframe": "5mins",
  "n_splits": 5,
  "test_size": 400,
  "scheme": "expanding",
  "embargo": 16,
  "purge": 16,
  "threshold_grid": [
    0.9
  ],
  "folds": [
    {
      "fold": 0,
      "n_train": 7484,
      "n_test": 400,
      "roc_auc": 0.8498701298701299,
      "pr_auc": 0.31372527397426364,
      "thresholds": [
        {
          "thr": 0.9,
          "n_trades": 0,
          "ev": -4.0
        }
      ]
    },
    {
      "fold": 1,
      "n_train": 7884,
      "n_test": 400,
      "roc_auc": 0.8497061293031065,
      "pr_auc": 0.03385103308576295,
      "thresholds": [
        {
          "thr": 0.9,
          "n_trades": 0,
          "ev": -4.0
        }
      ]
    },
    {
      "fold": 2,
      "n_train": 8284,
      "n_test": 400,
      "roc_auc": 0.8148517892796806,
      "pr_auc": 0.3509201136917898,
      "thresholds": [
        {
          "thr": 0.9,
          "n_trades": 0,
          "ev": -4.0
        }
      ]
    },
    {
      "fold": 3,
      "n_train": 8684,
      "n_test": 400,
      "roc_auc": 0.8734270910436714,
      "pr_auc": 0.1954573472229842,
      "thresholds": [
        {
          "thr": 0.9,
          "n_trades": 0,
          "ev": -4.0
        }
      ]
    },
    {
      "fold": 4,
      "n_train": 9084,
      "n_test": 400,
      "roc_auc": 0.8258974358974358,
      "pr_auc": 0.07626225856483049,
      "thresholds": [
        {
          "thr": 0.9,
          "n_trades": 0,
          "ev": -4.0
        }
      ]
    }
  ],
  "oof": {
    "n_samples": 2000,
    "oof_eval": {
      "oof_thresholds": [
        {
          "thr": 0.9,
          "n_trades": 0,
          "hit_rate": NaN,
          "ev": -4.0,
          "ev_lb": -4.0
        }
      ],
      "best_oof_by_ev_lb": {
        "thr": 0.9,
        "n_trades": 0,
        "hit_rate": NaN,
        "ev": -4.0,
        "ev_lb": -4.0
      }
    }
  },
  "metrics_mean": {
    "roc_auc": 0.8427505150788048,
    "pr_auc": 0.19404320530792624
  },
  "metrics_std": {
    "roc_auc": 0.02292644202689663,
    "pr_auc": 0.1400625263932542
  },
  "ev_at_recommended": {
    "per_fold": [],
    "mean": NaN,
    "std": NaN,
    "folds_covered": 0
  },
  "recommended_threshold": null,
  "recommended_by": null
}